WebListen_STTPM/__init__.py
WebListen_STTPM-0.1.dist-info/METADATA
WebListen_STTPM-0.1.dist-info/WHEEL
WebListen_STTPM-0.1.dist-info/top_level.txt
WebListen_STTPM-0.1.dist-info/RECORD
