Metadata-Version: 2.1
Name: WebListen-STTPM
Version: 0.1
Summary: This is speech to text package created by the author
Author: Prajurjya Mohapatra
Author-email: mrperfectprajurjya@gmail.com
